<?xml version="1.0" encoding="UTF-8"?>
<userOverrides>
    <override>
        <path>C:\Users\ncer\Desktop\四轴飞行器\Src\freertos.c</path>
        <encoding>UTF-8</encoding>
    </override>
    <override>
        <path>C:\Users\ncer\Desktop\四轴飞行器\Src\main.c</path>
        <encoding>UTF-8</encoding>
    </override>
    <override>
        <path>C:\Users\ncer\Desktop\四轴飞行器\Src\tim.c</path>
        <encoding>UTF-8</encoding>
    </override>
    <override>
        <path>C:\Users\ncer\Desktop\四轴飞行器\mydrivers\command.c</path>
        <encoding>UTF-8</encoding>
    </override>
    <override>
        <path>C:\Users\ncer\Desktop\四轴飞行器\mydrivers\nrf24l01.h</path>
        <encoding>UTF-8</encoding>
    </override>
</userOverrides>
